Metadata-Version: 1.1
Name: music-score
Version: 1.1.3
Summary: A program that using re module to analyze music score (simplified score).使用re模块解析曲谱(简谱)的程序。
Home-page: https://github.com/qfcy/Python/blob/main/music.py
Author: 七分诚意 qq:3076711200 百度贴吧账号:qfcy_
Author-email: 3076711200@qq.com
License: UNKNOWN
Keywords: music,music score,song,winsound,声音
Platform: win32
Classifier: Programming Language :: Python
Classifier: Topic :: Multimedia :: Sound/Audio
Classifier: Natural Language :: Chinese (Simplified)
